shadapi/__init__.py
shadapi/util.py
shadapi/accounts/__init__.py
shadapi/accounts/_client.py
shadapi/accounts/client.py
shadapi/accounts/handler.py
shadapi/accounts/connections/__init__.py
shadapi/accounts/methods/__init__.py
shadapi/bots/__init__.py
shadapi/bots/client.py
shadapi/bots/connections.py
shadapi/bots/methods.py
shadapi/bots/requests.py
shadapi/crypto/__init__.py
shadapi/exceptions/__init__.py
shadapi-0.2.0.dist-info/LICENSE
shadapi-0.2.0.dist-info/WHEEL
shadapi-0.2.0.dist-info/METADATA
shadapi-0.2.0.dist-info/RECORD
