Metadata-Version: 2.1
Name: shadapi
Version: 0.2.0
Summary: Read the latest Real Python tutorials
Keywords: shad,shadapi,shadio,chat,bot,robot,asyncio
Author: HoseanRC
Requires-Python: >=3.7
Classifier: Programming Language :: Python :: 3.7
Classifier: Programming Language :: Python :: 3.8
Classifier: Programming Language :: Python :: 3.9
Classifier: Programming Language :: Python :: 3.10
Classifier: Programming Language :: Python :: 3.11
Classifier: Programming Language :: Python :: 3.12
Classifier: License :: OSI Approved :: GNU Lesser General Public License v3 (LGPLv3)
Classifier: Topic :: Internet
Classifier: Topic :: Communications
Classifier: Topic :: Communications :: Chat
Classifier: Topic :: Software Development :: Libraries
Classifier: Topic :: Software Development :: Libraries :: Python Modules
Classifier: Topic :: Software Development :: Libraries :: Application Frameworks
Requires-Dist: wheel
Requires-Dist: pycryptodome
Requires-Dist: websockets
Requires-Dist: pybase64
Requires-Dist: aiohttp
Requires-Dist: mutagen
Requires-Dist: TinyTag
Requires-Dist: urllib3
Project-URL: Github, https://github.com/HoseanRC/shad-api
